README.md
setup.cfg
setup.py
src/pdp_lgtm/__init__.py
src/pdp_lgtm/config.py
src/pdp_lgtm/history.py
src/pdp_lgtm/pdp.py
src/pdp_lgtm.egg-info/PKG-INFO
src/pdp_lgtm.egg-info/SOURCES.txt
src/pdp_lgtm.egg-info/dependency_links.txt
src/pdp_lgtm.egg-info/entry_points.txt
src/pdp_lgtm.egg-info/not-zip-safe
src/pdp_lgtm.egg-info/top_level.txt