Metadata-Version: 2.1
Name: pdp-lgtm
Version: 0.1.4
Summary: party of dope pajamas looks good to me.
Home-page: https://github.com/timlyrics/pdp-lgtm
Author: Shaoqing Tan
Author-email: tansq7@gmail.com
License: MIT
Platform: UNKNOWN
